langchain_kggen/__init__.py
langchain_kggen/kggen.py
langchain_kggen/clustering/get_clusters.py
langchain_kggen/extractors/get_entities.py
langchain_kggen/extractors/get_relations.py
langchain_kggen/models/state.py
langchain_kggen/utils/chunk.py
langchain_kggen/utils/viz.py
langchain_kggen-0.1.3.dist-info/licenses/LICENSE
langchain_kggen-0.1.3.dist-info/METADATA
langchain_kggen-0.1.3.dist-info/WHEEL
langchain_kggen-0.1.3.dist-info/top_level.txt
langchain_kggen-0.1.3.dist-info/RECORD
