Metadata-Version: 2.4
Name: langchain-kggen
Version: 0.1.3
Summary: A powerful knowledge graph generation library using LangChain and LLM models
Author-email: Vasudev Gupta <guptavasudelhi@gmail.com>
Project-URL: Homepage, https://github.com/vasudevgupta31/langchain-kggen.git
Project-URL: Bug Reports, https://github.com/vasudevgupta31/langchain-kggen.git/issues
Project-URL: Source, https://github.com/vasudevgupta31/langchain-kggen.git
Keywords: knowledge-graph,langchain,llm,nlp,entity-extraction,relation-extraction,graph-generation,artificial-intelligence
Classifier: Development Status :: 3 - Alpha
Classifier: Intended Audience :: Developers
Classifier: Intended Audience :: Science/Research
Classifier: License :: OSI Approved :: MIT License
Classifier: Operating System :: OS Independent
Classifier: Programming Language :: Python :: 3
Classifier: Programming Language :: Python :: 3.8
Classifier: Programming Language :: Python :: 3.9
Classifier: Programming Language :: Python :: 3.10
Classifier: Programming Language :: Python :: 3.11
Classifier: Programming Language :: Python :: 3.12
Classifier: Topic :: Scientific/Engineering :: Artificial Intelligence
Classifier: Topic :: Software Development :: Libraries :: Python Modules
Classifier: Topic :: Text Processing :: Linguistic
Requires-Python: >=3.8
License-File: LICENSE
Requires-Dist: langchain-core>=0.3.6
Requires-Dist: langchain>=0.3.25
Requires-Dist: pydantic>=2.0.0
Requires-Dist: nltk>=3.8
Provides-Extra: dev
Requires-Dist: pytest>=7.0; extra == "dev"
Requires-Dist: black>=23.0; extra == "dev"
Requires-Dist: flake8>=6.0; extra == "dev"
Requires-Dist: mypy>=1.0; extra == "dev"
Requires-Dist: pre-commit>=3.0; extra == "dev"
Requires-Dist: networkx>=3.5; extra == "dev"
Dynamic: license-file
